iminspect/__init__.py
iminspect/__main__.py
iminspect/imgview.py
iminspect/inputs.py
iminspect/inspection_utils.py
iminspect/inspection_widgets.py
iminspect/inspector.py
iminspect/iminspect_assets/iminspect.svg
iminspect-1.4.1.dist-info/LICENSE
iminspect-1.4.1.dist-info/METADATA
iminspect-1.4.1.dist-info/WHEEL
iminspect-1.4.1.dist-info/top_level.txt
iminspect-1.4.1.dist-info/RECORD
