Metadata-Version: 2.1
Name: iminspect
Version: 1.4.1
Summary: Qt-based GUI to visualize image-like data
Author-email: snototter <snototter@users.noreply.github.com>
License: MIT License
Project-URL: homepage, https://github.com/snototter/iminspect
Classifier: Programming Language :: Python :: 3
Classifier: License :: OSI Approved :: MIT License
Classifier: Operating System :: OS Independent
Requires-Python: >=3.8
License-File: LICENSE
Requires-Dist: numpy
Requires-Dist: qimage2ndarray
Requires-Dist: qtpy
Requires-Dist: vito
Provides-Extra: pyqt5
Requires-Dist: PyQt5 ; extra == 'pyqt5'
Provides-Extra: pyqt6
Requires-Dist: PyQt6 ; extra == 'pyqt6'
Provides-Extra: pyside2
Requires-Dist: PySide2 ; extra == 'pyside2'
Provides-Extra: pyside6
Requires-Dist: PySide6 ; extra == 'pyside6'
